{
  "type": "FeatureCollection",
  "features": [
    {
      "type": "Feature",
      "properties": {},
      "geometry": {
        "coordinates": [
          [
            110.3436721298981,
            -7.668721153604778
          ],
          [
            110.34352014673289,
            -7.668951999216816
          ],
          [
            110.34337635902483,
            -7.669058875419893
          ],
          [
            110.34314629869044,
            -7.669693007007638
          ],
          [
            110.34275807187748,
            -7.669636006453956
          ],
          [
            110.34209664841882,
            -7.6693367534232095
          ],
          [
            110.34061275703112,
            -7.674251937042513
          ],
          [
            110.34059347232619,
            -7.674516377092232
          ],
          [
            110.34091890357416,
            -7.674692993102823
          ],
          [
            110.34101963229375,
            -7.67480049846472
          ],
          [
            110.34102738065576,
            -7.675069261750764
          ],
          [
            110.34097487333656,
            -7.675451350448213
          ],
          [
            110.34064527136456,
            -7.676104647761562
          ],
          [
            110.34046069426074,
            -7.6761699774375245
          ],
          [
            110.34017064452576,
            -7.676104647761562
          ],
          [
            110.34003880373757,
            -7.676326768619759
          ],
          [
            110.33866765953678,
            -7.680703832429813
          ],
          [
            110.34152537516604,
            -7.686977237917233
          ]
        ],
        "type": "LineString"
      }
    }
  ]
}