{
    "type": "FeatureCollection",
    "features": [
      {
        "type": "Feature",
        "properties": {},
        "geometry": {
          "coordinates": [
            [
              110.34198194082416,
              -7.687930085034083
            ],
            [
              110.3386022843689,
              -7.68068439739119
            ],
            [
              110.33883804131727,
              -7.680266434109441
            ],
            [
              110.34002536039611,
              -7.676351320789934
            ],
            [
              110.34012250468322,
              -7.67612668204724
            ],
            [
              110.34050028802812,
              -7.676148076217842
            ],
            [
              110.34102458211532,
              -7.675395557448766
            ],
            [
              110.34104266122137,
              -7.6747505403032505
            ],
            [
              110.34064492087907,
              -7.674589285863931
            ],
            [
              110.34059193774249,
              -7.674208941974726
            ],
            [
              110.34179157629603,
              -7.670381190110945
            ],
            [
              110.34209653045912,
              -7.669329822786338
            ],
            [
              110.34259739288154,
              -7.669581718105007
            ],
            [
              110.34309825530386,
              -7.669692848344781
            ],
            [
              110.34323281535762,
              -7.669529857316036
            ],
            [
              110.34338232652806,
              -7.669055701241334
            ],
            [
              110.34359911772452,
              -7.668833440399894
            ]
          ],
          "type": "LineString"
        }
      }
    ]
  }